pygraph.py
pygraph_02-0.1.0.dist-info/WHEEL
pygraph_02-0.1.0.dist-info/METADATA
pygraph_02-0.1.0.dist-info/RECORD
